setup.py
JnaneswarADItest/__init__.py
JnaneswarADItest/calculator.py
JnaneswarPackagetest.egg-info/PKG-INFO
JnaneswarPackagetest.egg-info/SOURCES.txt
JnaneswarPackagetest.egg-info/dependency_links.txt
JnaneswarPackagetest.egg-info/top_level.txt